cache3/__init__.py
cache3/base.py
cache3/disk.py
cache3/memory.py
cache3/setting.py
cache3/utils.py
cache3/validate.py
pycache3-0.1.1.dist-info/LICENSE
pycache3-0.1.1.dist-info/METADATA
pycache3-0.1.1.dist-info/WHEEL
pycache3-0.1.1.dist-info/top_level.txt
pycache3-0.1.1.dist-info/RECORD
